pykneer/__init__.py
pykneer/elastix_transformix.py
pykneer/find_reference_for_nb.py
pykneer/find_reference_functions.py
pykneer/find_reference_random_gen.py
pykneer/morphology_for_nb.py
pykneer/morphology_functions.py
pykneer/preprocessing_for_nb.py
pykneer/pykneer_io.py
pykneer/relaxometry_for_nb.py
pykneer/relaxometry_functions.py
pykneer/segmentation_quality_for_nb.py
pykneer/segmentation_sa_for_nb.py
pykneer/sitk_functions.py
pykneer/cylinder_fitting/__init__.py
pykneer/cylinder_fitting/analysis.py
pykneer/cylinder_fitting/fitting.py
pykneer/cylinder_fitting/geometry.py
pykneer/cylinder_fitting/visualize.py
pykneer/elastix/Darwin/LICENSE
pykneer/elastix/Darwin/NOTICE
pykneer/elastix/Darwin/elastix
pykneer/elastix/Darwin/libANNlib.dylib
pykneer/elastix/Darwin/transformix
pykneer/elastix/Linux/LICENSE
pykneer/elastix/Linux/NOTICE
pykneer/elastix/Linux/elastix
pykneer/elastix/Linux/libANNlib.so
pykneer/elastix/Linux/transformix
pykneer/elastix/Windows/ANNlib.dll
pykneer/elastix/Windows/LICENSE
pykneer/elastix/Windows/NOTICE
pykneer/elastix/Windows/elastix.exe
pykneer/elastix/Windows/transformix.exe
pykneer/parameterFiles/MR_iparam_rigid.txt
pykneer/parameterFiles/MR_iparam_similarity.txt
pykneer/parameterFiles/MR_iparam_spline.txt
pykneer/parameterFiles/MR_param_rigid.txt
pykneer/parameterFiles/MR_param_similarity.txt
pykneer/parameterFiles/MR_param_spline.txt
pykneer-0.0.6.3.dist-info/LICENSE
pykneer-0.0.6.3.dist-info/METADATA
pykneer-0.0.6.3.dist-info/WHEEL
pykneer-0.0.6.3.dist-info/top_level.txt
pykneer-0.0.6.3.dist-info/RECORD
